Workbook

Sheet Contratos
A1: id contrato | B1: Nombre | C1: Edificio | D1: Piso | E1: Fecha inicio | F1: Fecha fin | G1: Activo
A2: c40dcd0a-2212-45b3-b5d4-2aac8818bdf9 | B2: Ana | C2: Edificio 1 gaitán | D2: 1 | E2: 45545 | F2: =DATE(YEAR(E2),MONTH(E2)+6,DAY(E2)) -> 45726 | G2: FALSE
A3: 0f257e4c-3331-4e0e-869e-42c5a332a2a1 | B3: Ana | C3: Edificio 1 gaitán | D3: 1 | E3: 45737 | F3: =DATE(YEAR(E3),MONTH(E3)+6,DAY(E3)) -> 45921 | G3: FALSE
A4: 3dcc043e-cebd-4562-843a-73004bc5a5fb | B4: Ana | C4: Edificio 1 gaitán | D4: 1 | E4: 45921 | F4: =DATE(YEAR(E4),MONTH(E4)+6,DAY(E4)) -> 46102 | G4: TRUE
A5: ec860adc-defd-41d8-a89b-21d87b7ea128 | B5: Angelica | C5: Edificio 3 gaitán | D5: 3 | E5: 45604 | F5: =DATE(YEAR(E5),MONTH(E5)+6,DAY(E5)) -> 45785 | G5: FALSE
A6: ae88cdb7-93b0-42cd-bda5-e4576643e9c7 | B6: Angelica | C6: Edificio 3 gaitán | D6: 3 | E6: 45785 | F6: =DATE(YEAR(E6),MONTH(E6)+6,DAY(E6)) -> 45969 | G6: FALSE
A7: f60b893f-8aac-444a-b58c-711ee16b899d | B7: Bleikes | C7: Edificio 3 gaitán | D7: 2 | E7: 45136 | F7: =DATE(YEAR(E7),MONTH(E7)+6,DAY(E7)) -> 45320 | G7: FALSE
A8: 4665eec5-beab-4ad7-94aa-2367bd5ad522 | B8: Bleikes | C8: Edificio 3 gaitán | D8: 2 | E8: 45320 | F8: =DATE(YEAR(E8),MONTH(E8)+6,DAY(E8)) -> 45502 | G8: FALSE
A9: 5c552dcf-ebef-4bfe-aee2-c4a6981c0f3a | B9: Bleikes | C9: Edificio 3 gaitán | D9: 2 | E9: 45502 | F9: =DATE(YEAR(E9),MONTH(E9)+6,DAY(E9)) -> 45686 | G9: FALSE
A10: 4c0d2b4b-0d3e-42de-af57-9305df4b2c02 | B10: Bleikes | C10: Edificio 3 gaitán | D10: 2 | E10: 45686 | F10: =DATE(YEAR(E10),MONTH(E10)+6,DAY(E10)) -> 45867 | G10: FALSE
A11: 359216a7-8ba9-4e24-8cac-7dc225c9d6e1 | B11: Bleikes | C11: Edificio 3 gaitán | D11: 2 | E11: 45867 | F11: =DATE(YEAR(E11),MONTH(E11)+6,DAY(E11)) -> 46051 | G11: TRUE
A12: 4768bece-ab83-433d-8e6e-3a9988dd03b1 | B12: Carlos Rios | C12: Edificio manantial | D12: 3 | E12: 45505 | F12: =DATE(YEAR(E12),MONTH(E12)+6,DAY(E12)) -> 45689 | G12: FALSE
A13: bd3eeb6f-a14f-42cf-9deb-94f16f5eee70 | B13: Carlos Rios | C13: Edificio manantial | D13: 3 | E13: 45689 | F13: =DATE(YEAR(E13),MONTH(E13)+6,DAY(E13)) -> 45870 | G13: FALSE
... A68: f2b5f4e7-1f87-4e12-8e0e-4963e89c092a | B68: Yuranis | C68: Edificio 3 gaitán | D68: 4 | E68: 45645 | F68: =DATE(YEAR(E68),MONTH(E68)+6,DAY(E68)) -> 45827 | G68: FALSE

Sheet Tabla dinamica
A1: Etiquetas de fila | B1: Suma de TOTAL | D1: TIPO | E1: (Todas) | K1: NOMBRE PROPIETARIO | L1: Gustavo
A2: 2025 | B2: 98305227 | D2: MES | E2: Diciembre
A3: 45667 | B3: 8221690 | D3: ANIO | E3: 2025 | K3: FECHA | L3: MES | M3: ANIO | N3: TIPO | O3: VALOR | P3: CUOTA ADMINISTRACION | Q3: FONDO INMUEBLE | R3: TOTAL
A4: 45698 | B4: 8221690 | K4: 45667 | L4: Diciembre | M4: 2024 | N4: ARRIENDO | O4: 600000 | P4: 60000 | Q4: 0 | R4: 540000
A5: 45730 | B5: 8490690 | D5: Etiquetas de fila | E5: Suma de VALOR | F5: Suma de CUOTA ADMINISTRACION | G5: Suma de FONDO INMUEBLE | H5: Suma de TOTAL | K5: 45698 | L5: Enero | M5: 2025 | N5: ARRIENDO | O5: 600000 | P5: 60000 | Q5: 0 | R5: 540000
A6: 45755 | B6: 8285670 | D6: Edificio 1 gaitán | E6: 2030300 | F6: 199030 | G6: 40000 | H6: 1791270 | K6: 45730 | L6: Febrero | M6: 2025 | N6: ARRIENDO | O6: 600000 | P6: 60000 | Q6: 0 | R6: 540000
A7: 45786 | B7: 8315100 | D7: Edificio 2 gaitán | E7: 2152200 | F7: 209220 | G7: 60000 | H7: 1882980 | K7: 45755 | L7: Marzo | M7: 2025 | N7: ARRIENDO | O7: 600000 | P7: 60000 | Q7: 0 | R7: 540000
A8: 45835 | B8: 8355132 | D8: Edificio 3 gaitán | E8: 3053700 | F8: 297370 | G8: 80000 | H8: 2676330 | K8: 45786 | L8: Abril | M8: 2025 | N8: ARRIENDO | O8: 600000 | P8: 60000 | Q8: 0 | R8: 540000
A9: 45846 | B9: 7174242 | D9: Edificio manantial | E9: 2710320 | F9: 263032 | G9: 80000 | H9: 2367288 | K9: 45835 | L9: Mayo | M9: 2025 | N9: ARRIENDO | O9: 631200 | P9: 63120 | Q9: 0 | R9: 568080
A10: 45877 | B10: 7876242 | D10: Total general | E10: 9946520 | F10: 968652 | G10: 260000 | H10: 8717868 | K10: 45846 | L10: Junio | M10: 2025 | N10: ARRIENDO | O10: 631200 | P10: 63120 | Q10: 0 | R10: 568080
A11: 45910 | B11: 7898242 | K11: 45877 | L11: Julio | M11: 2025 | N11: ARRIENDO | O11: 631200 | P11: 63120 | Q11: 0 | R11: 568080
A12: 45939 | B12: 8755465 | K12: 45910 | L12: Agosto | M12: 2025 | N12: ARRIENDO | O12: 631200 | P12: 63120 | Q12: 0 | R12: 568080
A13: 45969 | B13: 8642132 | K13: 45939 | L13: Septiembre | M13: 2025 | N13: ARRIENDO | O13: 631200 | P13: 63120 | Q13: 0 | R13: 568080
A14: 46002 | B14: 8068932 | K14: 45969 | L14: Octubre | M14: 2025 | N14: ARRIENDO | O14: 631200 | P14: 63120 | Q14: 0 | R14: 568080
A15: 2026 | B15: 8717868 | K15: 46002 | L15: Noviembre | M15: 2025 | N15: ARRIENDO | O15: 631200 | P15: 63120 | Q15: 0 | R15: 568080
A16: 46031 | B16: 8717868 | K16: 46031 | L16: Diciembre | M16: 2025 | N16: ARRIENDO | O16: 631200 | P16: 63120 | Q16: 0 | R16: 568080
A17: Total general | B17: 107023095 | K17: Total general
D20: Nombre | E20: Gustavo
D22: Fecha inicio | E22: Fecha fin | F22: Activo
D23: 43594 | E23: 43778 | F23: FALSO
D24: 43778 | E24: 43960 | F24: FALSO
D25: 43960 | E25: 44144 | F25: FALSO
D26: 44144 | E26: 44325 | F26: FALSO
D27: 44325 | E27: 44509 | F27: FALSO
D28: 44509 | E28: 44690 | F28: FALSO
D29: 44690 | E29: 44874 | F29: FALSO
D30: 44874 | E30: 45055 | F30: FALSO
D31: 45055 | E31: 45239 | F31: FALSO
D32: 45239 | E32: 45421 | F32: FALSO
D33: 45421 | E33: 45605 | F33: FALSO
D34: 45605 | E34: 45786 | F34: FALSO
... D36: 45970 | E36: 46151 | F36: VERDADERO
D37: Total general

Sheet Pagos
A1: contrato_arriendo_id | B1: tipo | C1: mes | D1: anio | E1: fecha_pago | F1: EDIFICIO | G1: PISO | H1: NOMBRE PROPIETARIO | I1: valor_arriendo | J1: cuota_administracion | K1: fondo_inmueble | L1: total_neto
A2: {=_xlfn.XLOOKUP(1,(Contratos!$B$2:$B$203=H2)*(Contratos!$C$2:$C$203=F2)*(Contratos!$D$2:$D$203=G2)*(DATE(D2,MATCH(C2,{"Enero";"Febrero";"Marzo";"Abril";"Mayo";"Junio";"Julio";"Agosto";"Septiembre";"Octubre";"Noviembre";"Diciembre"},0),1)>=DATE(YEAR(Contratos!$E$2:$E$203),MONTH(Contratos!$E$2:$E$203),1))*(DATE(D2,MATCH(C2,{"Enero";"Febrero";"Marzo";"Abril";"Mayo";"Junio";"Julio";"Agosto";"Septiembre";"Octubre";"Noviembre";"Diciembre"},0),1)<=DATE(YEAR(Contratos!$F$2:$F$203),MONTH(Contratos!$F$2:$F$203),1)),Contratos!$A$2:$A$203,"")} -> c40dcd0a-2212-45b3-b5d4-2aac8818bdf9 | B2: ARRIENDO | C2: Diciembre | D2: 2024 | E2: 45667 | F2: Edificio 1 gaitán | G2: 1 | H2: Ana | I2: 700000 | J2: 68000 | K2: 20000 | L2: =I2-SUM(J2:K2) -> 612000
A3: {=_xlfn.XLOOKUP(1,(Contratos!$B$2:$B$203=H3)*(Contratos!$C$2:$C$203=F3)*(Contratos!$D$2:$D$203=G3)*(DATE(D3,MATCH(C3,{"Enero";"Febrero";"Marzo";"Abril";"Mayo";"Junio";"Julio";"Agosto";"Septiembre";"Octubre";"Noviembre";"Diciembre"},0),1)>=DATE(YEAR(Contratos!$E$2:$E$203),MONTH(Contratos!$E$2:$E$203),1))*(DATE(D3,MATCH(C3,{"Enero";"Febrero";"Marzo";"Abril";"Mayo";"Junio";"Julio";"Agosto";"Septiembre";"Octubre";"Noviembre";"Diciembre"},0),1)<=DATE(YEAR(Contratos!$F$2:$F$203),MONTH(Contratos!$F$2:$F$203),1)),Contratos!$A$2:$A$203,"")} -> e09f74db-f923-4e51-8bce-340da723f0cc | B3: ARRIENDO | C3: Diciembre | D3: 2024 | E3: 45667 | F3: Edificio 1 gaitán | G3: 2 | H3: Luz | I3: 630000 | J3: 61000 | K3: 20000 | L3: =I3-SUM(J3:K3) -> 549000
A4: {=_xlfn.XLOOKUP(1,(Contratos!$B$2:$B$203=H4)*(Contratos!$C$2:$C$203=F4)*(Contratos!$D$2:$D$203=G4)*(DATE(D4,MATCH(C4,{"Enero";"Febrero";"Marzo";"Abril";"Mayo";"Junio";"Julio";"Agosto";"Septiembre";"Octubre";"Noviembre";"Diciembre"},0),1)>=DATE(YEAR(Contratos!$E$2:$E$203),MONTH(Contratos!$E$2:$E$203),1))*(DATE(D4,MATCH(C4,{"Enero";"Febrero";"Marzo";"Abril";"Mayo";"Junio";"Julio";"Agosto";"Septiembre";"Octubre";"Noviembre";"Diciembre"},0),1)<=DATE(YEAR(Contratos!$F$2:$F$203),MONTH(Contratos!$F$2:$F$203),1)),Contratos!$A$2:$A$203,"")} -> 8e4d74fa-ec72-4872-a04b-81c46e2fbd96 | B4: ARRIENDO | C4: Diciembre | D4: 2024 | E4: 45667 | F4: Edificio 1 gaitán | G4: 3 | H4: Gustavo | I4: 600000 | J4: 60000 | K4: 0 | L4: =I4-SUM(J4:K4) -> 540000
A5: {=_xlfn.XLOOKUP(1,(Contratos!$B$2:$B$203=H5)*(Contratos!$C$2:$C$203=F5)*(Contratos!$D$2:$D$203=G5)*(DATE(D5,MATCH(C5,{"Enero";"Febrero";"Marzo";"Abril";"Mayo";"Junio";"Julio";"Agosto";"Septiembre";"Octubre";"Noviembre";"Diciembre"},0),1)>=DATE(YEAR(Contratos!$E$2:$E$203),MONTH(Contratos!$E$2:$E$203),1))*(DATE(D5,MATCH(C5,{"Enero";"Febrero";"Marzo";"Abril";"Mayo";"Junio";"Julio";"Agosto";"Septiembre";"Octubre";"Noviembre";"Diciembre"},0),1)<=DATE(YEAR(Contratos!$F$2:$F$203),MONTH(Contratos!$F$2:$F$203),1)),Contratos!$A$2:$A$203,"")} -> 9ce44e27-d7b6-4887-a696-e74e8e7b2a28 | B5: ARRIENDO | C5: Diciembre | D5: 2024 | E5: 45667 | F5: Edificio 2 gaitán | G5: 1 | H5: Johana | I5: 732100 | J5: 71210 | K5: 20000 | L5: =I5-SUM(J5:K5) -> 640890
A6: {=_xlfn.XLOOKUP(1,(Contratos!$B$2:$B$203=H6)*(Contratos!$C$2:$C$203=F6)*(Contratos!$D$2:$D$203=G6)*(DATE(D6,MATCH(C6,{"Enero";"Febrero";"Marzo";"Abril";"Mayo";"Junio";"Julio";"Agosto";"Septiembre";"Octubre";"Noviembre";"Diciembre"},0),1)>=DATE(YEAR(Contratos!$E$2:$E$203),MONTH(Contratos!$E$2:$E$203),1))*(DATE(D6,MATCH(C6,{"Enero";"Febrero";"Marzo";"Abril";"Mayo";"Junio";"Julio";"Agosto";"Septiembre";"Octubre";"Noviembre";"Diciembre"},0),1)<=DATE(YEAR(Contratos!$F$2:$F$203),MONTH(Contratos!$F$2:$F$203),1)),Contratos!$A$2:$A$203,"")} -> 9d4e93ec-8103-4ec7-94d4-480e0647a578 | B6: ARRIENDO | C6: Diciembre | D6: 2024 | E6: 45667 | F6: Edificio 2 gaitán | G6: 2 | H6: Victor | I6: 688000 | J6: 66800 | K6: 20000 | L6: =I6-SUM(J6:K6) -> 601200
A7: {=_xlfn.XLOOKUP(1,(Contratos!$B$2:$B$203=H7)*(Contratos!$C$2:$C$203=F7)*(Contratos!$D$2:$D$203=G7)*(DATE(D7,MATCH(C7,{"Enero";"Febrero";"Marzo";"Abril";"Mayo";"Junio";"Julio";"Agosto";"Septiembre";"Octubre";"Noviembre";"Diciembre"},0),1)>=DATE(YEAR(Contratos!$E$2:$E$203),MONTH(Contratos!$E$2:$E$203),1))*(DATE(D7,MATCH(C7,{"Enero";"Febrero";"Marzo";"Abril";"Mayo";"Junio";"Julio";"Agosto";"Septiembre";"Octubre";"Noviembre";"Diciembre"},0),1)<=DATE(YEAR(Contratos!$F$2:$F$203),MONTH(Contratos!$F$2:$F$203),1)),Contratos!$A$2:$A$203,"")} -> 3c91b9e4-e30d-43c4-93ec-843b4e0debfe | B7: ARRIENDO | C7: Diciembre | D7: 2024 | E7: 45667 | F7: Edificio 2 gaitán | G7: 3 | H7: Melissa | I7: 601000 | J7: 58000 | K7: 20000 | L7: =I7-SUM(J7:K7) -> 523000
A8: {=_xlfn.XLOOKUP(1,(Contratos!$B$2:$B$203=H8)*(Contratos!$C$2:$C$203=F8)*(Contratos!$D$2:$D$203=G8)*(DATE(D8,MATCH(C8,{"Enero";"Febrero";"Marzo";"Abril";"Mayo";"Junio";"Julio";"Agosto";"Septiembre";"Octubre";"Noviembre";"Diciembre"},0),1)>=DATE(YEAR(Contratos!$E$2:$E$203),MONTH(Contratos!$E$2:$E$203),1))*(DATE(D8,MATCH(C8,{"Enero";"Febrero";"Marzo";"Abril";"Mayo";"Junio";"Julio";"Agosto";"Septiembre";"Octubre";"Noviembre";"Diciembre"},0),1)<=DATE(YEAR(Contratos!$F$2:$F$203),MONTH(Contratos!$F$2:$F$203),1)),Contratos!$A$2:$A$203,"")} -> e919ee59-138a-4725-be6c-8f7c401f3312 | B8: ARRIENDO | C8: Diciembre | D8: 2024 | E8: 45667 | F8: Edificio 3 gaitán | G8: 1 | H8: Juan Olmos | I8: 780000 | J8: 76000 | K8: 20000 | L8: =I8-SUM(J8:K8) -> 684000
A9: {=_xlfn.XLOOKUP(1,(Contratos!$B$2:$B$203=H9)*(Contratos!$C$2:$C$203=F9)*(Contratos!$D$2:$D$203=G9)*(DATE(D9,MATCH(C9,{"Enero";"Febrero";"Marzo";"Abril";"Mayo";"Junio";"Julio";"Agosto";"Septiembre";"Octubre";"Noviembre";"Diciembre"},0),1)>=DATE(YEAR(Contratos!$E$2:$E$203),MONTH(Contratos!$E$2:$E$203),1))*(DATE(D9,MATCH(C9,{"Enero";"Febrero";"Marzo";"Abril";"Mayo";"Junio";"Julio";"Agosto";"Septiembre";"Octubre";"Noviembre";"Diciembre"},0),1)<=DATE(YEAR(Contratos!$F$2:$F$203),MONTH(Contratos!$F$2:$F$203),1)),Contratos!$A$2:$A$203,"")} -> 5c552dcf-ebef-4bfe-aee2-c4a6981c0f3a | B9: ARRIENDO | C9: Diciembre | D9: 2024 | E9: 45667 | F9: Edificio 3 gaitán | G9: 2 | H9: Bleikes | I9: 764000 | J9: 74400 | K9: 20000 | L9: =I9-SUM(J9:K9) -> 669600
A10: {=_xlfn.XLOOKUP(1,(Contratos!$B$2:$B$203=H10)*(Contratos!$C$2:$C$203=F10)*(Contratos!$D$2:$D$203=G10)*(DATE(D10,MATCH(C10,{"Enero";"Febrero";"Marzo";"Abril";"Mayo";"Junio";"Julio";"Agosto";"Septiembre";"Octubre";"Noviembre";"Diciembre"},0),1)>=DATE(YEAR(Contratos!$E$2:$E$203),MONTH(Contratos!$E$2:$E$203),1))*(DATE(D10,MATCH(C10,{"Enero";"Febrero";"Marzo";"Abril";"Mayo";"Junio";"Julio";"Agosto";"Septiembre";"Octubre";"Noviembre";"Diciembre"},0),1)<=DATE(YEAR(Contratos!$F$2:$F$203),MONTH(Contratos!$F$2:$F$203),1)),Contratos!$A$2:$A$203,"")} -> ec860adc-defd-41d8-a89b-21d87b7ea128 | B10: ARRIENDO | C10: Diciembre | D10: 2024 | E10: 45667 | F10: Edificio 3 gaitán | G10: 3 | H10: Angelica | I10: 700000 | J10: 68000 | K10: 20000 | L10: =I10-SUM(J10:K10) -> 612000
A11: {=_xlfn.XLOOKUP(1,(Contratos!$B$2:$B$203=H11)*(Contratos!$C$2:$C$203=F11)*(Contratos!$D$2:$D$203=G11)*(DATE(D11,MATCH(C11,{"Enero";"Febrero";"Marzo";"Abril";"Mayo";"Junio";"Julio";"Agosto";"Septiembre";"Octubre";"Noviembre";"Diciembre"},0),1)>=DATE(YEAR(Contratos!$E$2:$E$203),MONTH(Contratos!$E$2:$E$203),1))*(DATE(D11,MATCH(C11,{"Enero";"Febrero";"Marzo";"Abril";"Mayo";"Junio";"Julio";"Agosto";"Septiembre";"Octubre";"Noviembre";"Diciembre"},0),1)<=DATE(YEAR(Contratos!$F$2:$F$203),MONTH(Contratos!$F$2:$F$203),1)),Contratos!$A$2:$A$203,"")} -> 165e1685-0b5f-46a9-8720-08682265922b | B11: ARRIENDO | C11: Diciembre | D11: 2024 | E11: 45667 | F11: Edificio 3 gaitán | G11: 4 | H11: Yuranis | I11: 620000 | J11: 60000 | K11: 20000 | L11: =I11-SUM(J11:K11) -> 540000
A12: {=_xlfn.XLOOKUP(1,(Contratos!$B$2:$B$203=H12)*(Contratos!$C$2:$C$203=F12)*(Contratos!$D$2:$D$203=G12)*(DATE(D12,MATCH(C12,{"Enero";"Febrero";"Marzo";"Abril";"Mayo";"Junio";"Julio";"Agosto";"Septiembre";"Octubre";"Noviembre";"Diciembre"},0),1)>=DATE(YEAR(Contratos!$E$2:$E$203),MONTH(Contratos!$E$2:$E$203),1))*(DATE(D12,MATCH(C12,{"Enero";"Febrero";"Marzo";"Abril";"Mayo";"Junio";"Julio";"Agosto";"Septiembre";"Octubre";"Noviembre";"Diciembre"},0),1)<=DATE(YEAR(Contratos!$F$2:$F$203),MONTH(Contratos!$F$2:$F$203),1)),Contratos!$A$2:$A$203,"")} -> 16fbb6a2-d237-4dd2-8a6d-7bd76aa8645c | B12: ARRIENDO | C12: Diciembre | D12: 2024 | E12: 45667 | F12: Edificio manantial | G12: 1 | H12: Henry | I12: 660000 | J12: 64000 | K12: 20000 | L12: =I12-SUM(J12:K12) -> 576000
A13: {=_xlfn.XLOOKUP(1,(Contratos!$B$2:$B$203=H13)*(Contratos!$C$2:$C$203=F13)*(Contratos!$D$2:$D$203=G13)*(DATE(D13,MATCH(C13,{"Enero";"Febrero";"Marzo";"Abril";"Mayo";"Junio";"Julio";"Agosto";"Septiembre";"Octubre";"Noviembre";"Diciembre"},0),1)>=DATE(YEAR(Contratos!$E$2:$E$203),MONTH(Contratos!$E$2:$E$203),1))*(DATE(D13,MATCH(C13,{"Enero";"Febrero";"Marzo";"Abril";"Mayo";"Junio";"Julio";"Agosto";"Septiembre";"Octubre";"Noviembre";"Diciembre"},0),1)<=DATE(YEAR(Contratos!$F$2:$F$203),MONTH(Contratos!$F$2:$F$203),1)),Contratos!$A$2:$A$203,"")} -> 09012b19-863a-4906-b34b-a89dcba8626e | B13: ARRIENDO | C13: Diciembre | D13: 2024 | E13: 45667 | F13: Edificio manantial | G13: 2 | H13: Yadeisy | I13: 670000 | J13: 65000 | K13: 20000 | L13: =I13-SUM(J13:K13) -> 585000
... A180: {=_xlfn.XLOOKUP(1,(Contratos!$B$2:$B$203=H180)*(Contratos!$C$2:$C$203=F180)*(Contratos!$D$2:$D$203=G180)*(DATE(D180,MATCH(C180,{"Enero";"Febrero";"Marzo";"Abril";"Mayo";"Junio";"Julio";"Agosto";"Septiembre";"Octubre";"Noviembre";"Diciembre"},0),1)>=DATE(YEAR(Contratos!$E$2:$E$203),MONTH(Contratos!$E$2:$E$203),1))*(DATE(D180,MATCH(C180,{"Enero";"Febrero";"Marzo";"Abril";"Mayo";"Junio";"Julio";"Agosto";"Septiembre";"Octubre";"Noviembre";"Diciembre"},0),1)<=DATE(YEAR(Contratos!$F$2:$F$203),MONTH(Contratos!$F$2:$F$203),1)),Contratos!$A$2:$A$203,"")} -> 1138e6b0-3b54-4f90-9461-f8f76393e615 | B180: ARRIENDO | C180: Diciembre | D180: 2025 | E180: 46031 | F180: Edificio manantial | G180: 4 | H180: Daniel | I180: 631200 | J180: 61120 | K180: 20000 | L180: =I180-SUM(J180:K180) -> 550080
